cwsc/__init__.py
cwscript/__init__.py
cwscript/highlight.py
cwscript/lang/ast.py
cwscript/lang/grammar/CWScriptLexer.interp
cwscript/lang/grammar/CWScriptLexer.py
cwscript/lang/grammar/CWScriptLexer.tokens
cwscript/lang/grammar/CWScriptParser.interp
cwscript/lang/grammar/CWScriptParser.py
cwscript/lang/grammar/CWScriptParser.tokens
cwscript/lang/grammar/CWScriptParserListener.py
cwscript/lang/grammar/CWScriptParserVisitor.py
cwscript/lang/parser.py
cwscript/main.py
cwscript/parser.py
cwscript/template.py
cwscript/util/context_env.py
cwscript/util/strings.py
cwsls/server.py
cwscript-0.1.0.dist-info/entry_points.txt
cwscript-0.1.0.dist-info/WHEEL
cwscript-0.1.0.dist-info/METADATA
cwscript-0.1.0.dist-info/RECORD
