Metadata-Version: 2.1
Name: cwscript
Version: 0.1.0
Summary: CWScript compiler and standard tooling.
Author: William Chen
Author-email: william@terran.one
Requires-Python: >=3.8,<4.0
Classifier: Programming Language :: Python :: 3
Classifier: Programming Language :: Python :: 3.8
Classifier: Programming Language :: Python :: 3.9
Requires-Dist: Jinja2 (>=3.0.3,<4.0.0)
Requires-Dist: Pygments (>=2.11.2,<3.0.0)
Requires-Dist: antlr4-python3-runtime (>=4.9.3,<5.0.0)
Requires-Dist: click (>=8.0.3,<9.0.0)
Requires-Dist: prompt-toolkit (>=3.0.24,<4.0.0)
Requires-Dist: pygls (>=0.11.3,<0.12.0)
Requires-Dist: python-fire (>=0.1.0,<0.2.0)
